gpay/__init__.py
gpay/gpay_api_client.py
gpay/response_models.py
gpay_sdk-1.0.1.dist-info/METADATA
gpay_sdk-1.0.1.dist-info/WHEEL
gpay_sdk-1.0.1.dist-info/top_level.txt
gpay_sdk-1.0.1.dist-info/RECORD
