Metadata-Version: 2.4
Name: gpay-sdk
Version: 1.0.1
Summary: GPay API Python Client Library
Home-page: https://github.com/Libya-Guide/GPay-Python-SDK
Author: Libya Guide for Information Technology and Training
Author-email: info@libyaguide.net
Classifier: Programming Language :: Python :: 3
Classifier: License :: OSI Approved :: MIT License
Classifier: Operating System :: OS Independent
Requires-Python: >=3.6
Requires-Dist: requests
Dynamic: author
Dynamic: author-email
Dynamic: classifier
Dynamic: description
Dynamic: description-content-type
Dynamic: home-page
Dynamic: requires-dist
Dynamic: requires-python
Dynamic: summary
